odoo/addons/hr_holidays_natural_period/README.rst
odoo/addons/hr_holidays_natural_period/__init__.py
odoo/addons/hr_holidays_natural_period/__manifest__.py
odoo/addons/hr_holidays_natural_period/i18n/ca.po
odoo/addons/hr_holidays_natural_period/i18n/es.po
odoo/addons/hr_holidays_natural_period/i18n/hr.po
odoo/addons/hr_holidays_natural_period/i18n/hr_holidays_natural_period.pot
odoo/addons/hr_holidays_natural_period/i18n/it.po
odoo/addons/hr_holidays_natural_period/models/__init__.py
odoo/addons/hr_holidays_natural_period/models/hr_leave.py
odoo/addons/hr_holidays_natural_period/models/hr_leave_type.py
odoo/addons/hr_holidays_natural_period/models/resource_calendar.py
odoo/addons/hr_holidays_natural_period/readme/CONTRIBUTORS.rst
odoo/addons/hr_holidays_natural_period/readme/DESCRIPTION.rst
odoo/addons/hr_holidays_natural_period/readme/USAGE.rst
odoo/addons/hr_holidays_natural_period/static/description/icon.png
odoo/addons/hr_holidays_natural_period/static/description/index.html
odoo/addons/hr_holidays_natural_period/tests/__init__.py
odoo/addons/hr_holidays_natural_period/tests/test_hr_leave.py
odoo14_addon_hr_holidays_natural_period-14.0.1.0.1.dev10.dist-info/METADATA
odoo14_addon_hr_holidays_natural_period-14.0.1.0.1.dev10.dist-info/WHEEL
odoo14_addon_hr_holidays_natural_period-14.0.1.0.1.dev10.dist-info/top_level.txt
odoo14_addon_hr_holidays_natural_period-14.0.1.0.1.dev10.dist-info/RECORD
